{
    "1.1 Tujuan Produk/Definisi": "",
    "1.2 Panduan Keamanan": "",
    "1.3 Penjelasan Simbol": "",
    "1.4 Singkatan": "",
    "2.0 Instalasi": "",
    "3.1 Antarmuka Pengguna": "",
    "3.2 Overview": "",
    "3.3 Manajemen Pasien": "",
    "3.4 Prosedur Pemantauan": "",
    "3.5 Perhitungan Medis": "",
    "3.6 Manajemen Rekaman & Tinjauan Hasil": "",
    "4.1 Inspeksi Umum": "Professional inspection and change Dust sensor failure maintenance Particulate matter cancels Need filter replacement out the filter Excessive dust accumulation on the front Clean the filter before used The air inlet and air outlet Reduce purification effect are blocked by foreign Remove foreign objects The machine is placed in Changing engine an unreasonable position placement Adjust the wind speed to Wind speed is not top class The battery in the remote Remote Control failed Replace the battery control is dead Inspection and Damage to the PCB or Panel button failure maintenance by professionals Medical Air Purifier (MAP-380) Wipe stains with a dry or damp cloth. • Turn off the unit before cleaning. • Do not rinse the unit with water. • Do not use cleaning fluids; use a small amount of neutral kitchen detergent. • Do not use decontamination powder, cleaning alkalis, alcohol, bleach, TRD, or solvents (they will cause deformation and discoloration). • When using a chemical cloth, please be aware of the side effects. It is recommended to clean the unit every 1 month or so. Medical Air Purifier (MAP-380) Clean the air inlet and outlet sensors  Use a clean, damp cloth to wipe away any dust or dirt from the air grill.  Use a vacuum cleaner with a brush attachment to clean the ventilation  Always clean the air inlet and outlet, as this will affect the product's purification effect.  Use a vacuum cleaner or a soft, damp cloth to remove any dirt from the inlet and outlet.  Use a flat-blade screwdriver to lift the sensor cover and clean the dust from the sensor hole with a cotton swab.  It is recommended to clean once a month. About use and operation Keep away from range children the unit near wet places , even when hand Otherwise, it may cause danger electric You wet , don't touch it . shock If not, will happen fire and electric shock . Medical Air Purifier (MAP-380) Do not insert needles, wires or Never use chlorine or acidic metal objects into the air inlet , detergents to clean the inside air outlet and other gaps. of the main unit. Otherwise, it may touch internal parts and Detergents can release toxic gases that are cause electric shock or injury . harmful to health. Never disassemble or modify Don't remove the filter during this machine without operation agreement . Otherwise, it may cause injury. Unauthorized dismantling or modification of electrical equipment may cause damage or About power cables, power plugs and sockets Connect with a power outlet in Do not touch the power plug a way full Failure in connecting with wet hands. the power outlet can result in connection current short or heat that results fire . This may cause electric shock. Don't using a damaged power outlet or loose Do not damage the power cord Before cleaning the device, be or socket. sure to unplug the power Do not use damaged cables as they may supply. cause electric shock, short circuit or fire Otherwise, the Machine may run suddenly accidents . and cause electric shock. Clean the power plug regularly. Do not use the power supply or If dust accumulates on the specified rating of the power plug, moisture can connected equipment, only use a 220V AC damage the insulation of the plug, resulting power supply. in a fire accident. Use of Universal sockets or other devices Unplug the power plug and clean with a dry exceeding the specified values may cause Medical Air Purifier (MAP-380) cloth. overheating and fire accidents. If the appliance is not used for a long time, the power plug should be removed. When cleaning or replacing the When cleaning or replacing the filter, please disconnect the filter, please disassemble it power first. carefully. Otherwise, accidents may occur. If you accidentally damage the filter , will affect the reliability of the unit. Do not place it in an unstable Clean the power plug regularly. place. This may cause electric shock, A place that is not stable will short circuit or accident. fire. produce vibrations in the unit and resulting in accidents . If the power cord is damaged, in order to avoid danger, it must be replaced by the manufacturer, maintenance department or other similar professional. Medical Air Purifier (MAP-380) MEDICAL AIR PURIFIER MANUAL BOOK ",
    "4.2 Pemeliharaan": "",
    "4.3 Perawatan": "",
    "4.4 Pembersihan": "",
    "5.0 Pemecahan Masalah": "",
    "6.1 Spesifikasi": "",
    "6.2 Kepatuhan Standar": "",
    "7.1 Garansi": "",
    "7.2 Informasi Kontak": ""
}